.gitignore
.installed.cfg
CHANGES.txt
MANIFEST.in
README.rst
README.txt
bootstrap.py
buildout.cfg
create_tag.sh
missing_versions.cfg
setup.py
versions.cfg
src/lovely/__init__.py
src/lovely.memcached.egg-info/PKG-INFO
src/lovely.memcached.egg-info/SOURCES.txt
src/lovely.memcached.egg-info/dependency_links.txt
src/lovely.memcached.egg-info/namespace_packages.txt
src/lovely.memcached.egg-info/not-zip-safe
src/lovely.memcached.egg-info/requires.txt
src/lovely.memcached.egg-info/top_level.txt
src/lovely/memcached/README.txt
src/lovely/memcached/__init__.py
src/lovely/memcached/configurator.py
src/lovely/memcached/configure.zcml
src/lovely/memcached/event.py
src/lovely/memcached/interfaces.py
src/lovely/memcached/lovely.memcached-configure.zcml
src/lovely/memcached/tests.py
src/lovely/memcached/utility.py
src/lovely/memcached/version.txt
src/lovely/memcached/browser/README.txt
src/lovely/memcached/browser/__init__.py
src/lovely/memcached/browser/configure.zcml
src/lovely/memcached/browser/ftesting.zcml
src/lovely/memcached/browser/stats.pt
src/lovely/memcached/browser/tests.py
src/lovely/memcached/testing/README.txt
src/lovely/memcached/testing/__init__.py
src/lovely/memcached/testing/memcache.py