Metadata-Version: 1.0
Name: lovely.memcached
Version: 0.2.2
Summary: A memcached client utiltiy for zope 3
Home-page: http://github.com/lovelysystems/lovely.memcached
Author: Lovely Systems
Author-email: office@lovelysystems.com
License: ZPL 2.1
Keywords: zope3 zope memcached cache ram
Platform: UNKNOWN
